Workbook

Sheet Historical
A1: Year | B1: Revenue | C1: Net Income
A2: 2020 | B2: 811 | C2: 176.2
A3: 2021 | B3: 1037.1 | C3: 279.9
A4: 2022 | B4: 1006.1 | C4: 215.5
A5: 2023 | B5: 837.6 | C5: 113.2
A6: 2024 | B6: 914.5 | C6: 106.2

Sheet Assumptions
A1: Variable | B1: Base | C1: Bull | D1: Bear
A2: Revenue Growth % | B2: 0.1 | C2: 0.15 | D2: 0.05
A3: COGS % of Revenue | B3: 0.7 | C3: 0.65 | D3: 0.75
A4: SG&A % of Revenue | B4: 0.15 | C4: 0.13 | D4: 0.17
A5: R&D % of Revenue | B5: 0.1 | C5: 0.09 | D5: 0.11
A6: Tax Rate | B6: 0.21 | C6: 0.21 | D6: 0.21
A8: Notes:
A9: Base Being Modeled

Sheet Forecast
A1: Year | B1: Revenue | C1: COGS | D1: Gross Profit | E1: SG&A | F1: R&D | G1: EBIT | H1: Net Income
A2: 2025 | B2: =Historical!B6*(1+Assumptions!B2)^1 -> 1005.95 | C2: =B2*Assumptions!B3 -> 704.165 | D2: =B2-C2 -> 301.785 | E2: =B2*Assumptions!B4 -> 150.8925 | F2: =B2*Assumptions!B5 -> 100.595 | G2: =D2-E2-F2 -> 50.2975 | H2: =G2*(1-Assumptions!B6) -> 39.735025
A3: 2026 | B3: =Historical!B6*(1+Assumptions!B2)^2 -> 1106.545 | C3: =B3*Assumptions!B3 -> 774.5815 | D3: =B3-C3 -> 331.9635 | E3: =B3*Assumptions!B4 -> 165.98175 | F3: =B3*Assumptions!B5 -> 110.6545 | G3: =D3-E3-F3 -> 55.32725 | H3: =G3*(1-Assumptions!B6) -> 43.708528
A4: 2027 | B4: =Historical!B6*(1+Assumptions!B2)^3 -> 1217.1995 | C4: =B4*Assumptions!B3 -> 852.03965 | D4: =B4-C4 -> 365.15985 | E4: =B4*Assumptions!B4 -> 182.57993 | F4: =B4*Assumptions!B5 -> 121.71995 | G4: =D4-E4-F4 -> 60.859975 | H4: =G4*(1-Assumptions!B6) -> 48.07938
A5: 2028 | B5: =Historical!B6*(1+Assumptions!B2)^4 -> 1338.9195 | C5: =B5*Assumptions!B3 -> 937.24362 | D5: =B5-C5 -> 401.67584 | E5: =B5*Assumptions!B4 -> 200.83792 | F5: =B5*Assumptions!B5 -> 133.89195 | G5: =D5-E5-F5 -> 66.945973 | H5: =G5*(1-Assumptions!B6) -> 52.887318
A6: 2029 | B6: =Historical!B6*(1+Assumptions!B2)^5 -> 1472.8114 | C6: =B6*Assumptions!B3 -> 1030.968 | D6: =B6-C6 -> 441.84342 | E6: =B6*Assumptions!B4 -> 220.92171 | F6: =B6*Assumptions!B5 -> 147.28114 | G6: =D6-E6-F6 -> 73.64057 | H6: =G6*(1-Assumptions!B6) -> 58.17605
